pyfabric/Fabric.py
pyfabric/__init__.py
pyfabric/Command/Command.py
pyfabric/Command/__init__.py
pyfabric/Entity/Entity.py
pyfabric/Entity/Inventory.py
pyfabric/Entity/__init__.py
pyfabric/Events/EventType.py
pyfabric/Events/__init__.py
pyfabric/Networking/Client.py
pyfabric/Networking/Response.py
pyfabric/Networking/__init__.py
pyfabric/World/World.py
pyfabric/World/__init__.py
pyfabric-1.0.6.dist-info/METADATA
pyfabric-1.0.6.dist-info/WHEEL
pyfabric-1.0.6.dist-info/licenses/LICENSE
pyfabric-1.0.6.dist-info/RECORD
