Metadata-Version: 2.1
Name: PyFabric
Version: 1.0.6
Summary: The python websocket for java minecraft
Project-URL: Homepage, https://github.com/ToberoCat/PyFabric
Project-URL: Documentation, https://github.com/ToberoCat/PyFabric/wiki
Project-URL: Bug Tracker, https://github.com/ToberoCat/PyFabric/issues
Author-email: Tobias Madlberger <tobias.madlberger@gmail.com>
License:                     GNU GENERAL PUBLIC LICENSE
Classifier: License :: OSI Approved :: MIT License
Classifier: Operating System :: OS Independent
Classifier: Programming Language :: Python :: 3
Requires-Python: >=3.7
